bib2json/__init__.py
bib2json/__main__.py
bib2json/converter.py
bib2json-0.1.0.dist-info/LICENSE
bib2json-0.1.0.dist-info/METADATA
bib2json-0.1.0.dist-info/WHEEL
bib2json-0.1.0.dist-info/entry_points.txt
bib2json-0.1.0.dist-info/top_level.txt
bib2json-0.1.0.dist-info/RECORD
