Metadata-Version: 2.2
Name: bib2json
Version: 0.1.0
Summary: Bib2JSON is a simple Python tool for converting BibTeX files to JSON format. It maintains the structure and content of your bibliographic entries while making them accessible in a more versatile machine-readable format. Originally created by [Brian Rabern](https://github.com/brianrabern/bib2json).
Author-email: student30204 <author@example.com>
Project-URL: Homepage, https://github.com/ah3243/bib2json
Project-URL: Issues, https://github.com/ah3243/bib2json/issues
Classifier: Programming Language :: Python :: 3
Classifier: Operating System :: OS Independent
Classifier: License :: OSI Approved :: MIT License
Requires-Python: >=3.8
License-File: LICENSE
Requires-Dist: bibtexparser>=1.0.0
